comiccrawler/__init__.py
comiccrawler/__main__.py
comiccrawler/analyzer.py
comiccrawler/batch_analyzer.py
comiccrawler/channel.py
comiccrawler/cli.py
comiccrawler/config.py
comiccrawler/core.py
comiccrawler/crawler.py
comiccrawler/download_manager.py
comiccrawler/episode.py
comiccrawler/episode_loader.py
comiccrawler/error.py
comiccrawler/filename_ext.py
comiccrawler/grabber.py
comiccrawler/image.py
comiccrawler/io.py
comiccrawler/logger.py
comiccrawler/mission.py
comiccrawler/mission_manager.py
comiccrawler/module_grabber.py
comiccrawler/profile.py
comiccrawler/safeprint.py
comiccrawler/save_path.py
comiccrawler/session_manager.py
comiccrawler/url.py
comiccrawler/util.py
comiccrawler/gui/__init__.py
comiccrawler/gui/cli_progress.py
comiccrawler/gui/core.py
comiccrawler/gui/dialog.py
comiccrawler/gui/main_window.py
comiccrawler/gui/select_episodes.py
comiccrawler/gui/table.py
comiccrawler/mods/_177pic.py
comiccrawler/mods/_99.py
comiccrawler/mods/__init__.py
comiccrawler/mods/aacomic.py
comiccrawler/mods/acgn.py
comiccrawler/mods/artstation.py
comiccrawler/mods/bilibili.py
comiccrawler/mods/bilibili_manga.py
comiccrawler/mods/buka.py
comiccrawler/mods/cartoonmad.py
comiccrawler/mods/chuixue.py
comiccrawler/mods/colamanga.py
comiccrawler/mods/copy.py
comiccrawler/mods/danbooru.py
comiccrawler/mods/deviantart.py
comiccrawler/mods/dm5.py
comiccrawler/mods/dmzj.py
comiccrawler/mods/dmzj_m.py
comiccrawler/mods/dmzj_www.py
comiccrawler/mods/eight.py
comiccrawler/mods/exh.py
comiccrawler/mods/facebook.py
comiccrawler/mods/fanbox.py
comiccrawler/mods/fantia.py
comiccrawler/mods/flickr.py
comiccrawler/mods/gelbooru.py
comiccrawler/mods/gufeng.py
comiccrawler/mods/hhxiee.py
comiccrawler/mods/iibq.py
comiccrawler/mods/imgbox.py
comiccrawler/mods/instagram.py
comiccrawler/mods/jpg4.py
comiccrawler/mods/kemono.py
comiccrawler/mods/konachan.py
comiccrawler/mods/linevoom.py
comiccrawler/mods/manhuabei_m.py
comiccrawler/mods/manhuadui.py
comiccrawler/mods/manhuaren.py
comiccrawler-2025.3.24.dist-info/METADATA
comiccrawler-2025.3.24.dist-info/WHEEL
comiccrawler-2025.3.24.dist-info/entry_points.txt
comiccrawler-2025.3.24.dist-info/top_level.txt
comiccrawler-2025.3.24.dist-info/RECORD
