Metadata-Version: 2.2
Name: comiccrawler
Version: 2025.3.24
Summary: An image crawler, including multiple modules and GUI.
Home-page: https://github.com/eight04/ComicCrawler
Author: eight
Author-email: eight04@gmail.com
License: MIT
Keywords: image,crawler
Classifier: Development Status :: 5 - Production/Stable
Classifier: Environment :: Console
Classifier: Environment :: Win32 (MS Windows)
Classifier: Intended Audience :: End Users/Desktop
Classifier: License :: OSI Approved :: MIT License
Classifier: Natural Language :: Chinese (Traditional)
Classifier: Operating System :: Microsoft :: Windows :: Windows 7
Classifier: Programming Language :: Python :: 3.6
Classifier: Programming Language :: Python :: 3.8
Classifier: Topic :: Internet
Requires-Python: >=3.10
Requires-Dist: belfrywidgets~=1.0
Requires-Dist: bidict~=0.23.1
Requires-Dist: brotli~=1.1
Requires-Dist: curl_cffi~=0.10.0
Requires-Dist: deno-vm~=0.6.0
Requires-Dist: desktop3~=0.5.3
Requires-Dist: docopt~=0.6.2
Requires-Dist: enlighten~=1.14
Requires-Dist: puremagic~=1.28
Requires-Dist: pycryptodomex~=3.21
Requires-Dist: pythreadworker~=0.10.0
Requires-Dist: safeprint~=0.2.0
Requires-Dist: uncurl~=0.0.11
Requires-Dist: urllib3~=2.3
Requires-Dist: yt-dlp~=2025.2
